sqlmin/__init__.py
sqlmin/sql_minifier.py
sqlmin-1.0.3.dist-info/LICENSE
sqlmin-1.0.3.dist-info/METADATA
sqlmin-1.0.3.dist-info/WHEEL
sqlmin-1.0.3.dist-info/entry_points.txt
sqlmin-1.0.3.dist-info/top_level.txt
sqlmin-1.0.3.dist-info/RECORD
