Metadata-Version: 2.1
Name: sqlmin
Version: 1.0.3
Summary: SQL Minifier
Home-page: https://github.com/enrique-rodriguez/sqlmin
Author: Enrique Rodriguez
Author-email: rodriguez.enrique.pr@gmail.com
Keywords: sql minifier,minify sql,sqlmin,minsql
License-File: LICENSE
